exmol/__init__.py
exmol/data.py
exmol/exmol.py
exmol/plot_utils.py
exmol/py.typed
exmol/version.py
exmol/lime_data/MACCSkeys.txt
exmol/lime_data/atom_pols.txt
exmol/lime_data/keys.pb
exmol/lime_data/smarts.txt
exmol/stoned/__init__.py
exmol/stoned/stoned.py
exmol-3.3.0.dist-info/licenses/LICENSE
exmol-3.3.0.dist-info/licenses/NOTICE.txt
exmol-3.3.0.dist-info/METADATA
exmol-3.3.0.dist-info/WHEEL
exmol-3.3.0.dist-info/top_level.txt
exmol-3.3.0.dist-info/RECORD
