Metadata-Version: 2.4
Name: exmol
Version: 3.3.0
Summary: Counterfactual generation with STONED SELFIES
Home-page: https://ur-whitelab.github.io/exmol/
Author: Aditi Seshadri, Geemi Wellawatte, Andrew White
Author-email: andrew.white@rochester.edu
License: MIT
Classifier: Programming Language :: Python :: 3
Classifier: License :: OSI Approved :: MIT License
Classifier: Operating System :: OS Independent
Classifier: Topic :: Scientific/Engineering :: Chemistry
Classifier: Topic :: Scientific/Engineering :: Artificial Intelligence
Classifier: Typing :: Typed
License-File: LICENSE
License-File: NOTICE.txt
Requires-Dist: selfies>=2.0.0
Requires-Dist: numpy
Requires-Dist: requests
Requires-Dist: tqdm
Requires-Dist: ratelimit
Requires-Dist: rdkit
Requires-Dist: scikit-learn
Requires-Dist: skunk>=0.4.0
Requires-Dist: importlib-resources
Requires-Dist: synspace
Requires-Dist: openai
Dynamic: author
Dynamic: author-email
Dynamic: classifier
Dynamic: description
Dynamic: description-content-type
Dynamic: home-page
Dynamic: license
Dynamic: license-file
Dynamic: requires-dist
Dynamic: summary
